MetaVisionary/__init__.py
MetaVisionary/few_shot_meta.py
MetaVisionary-0.2.dist-info/METADATA
MetaVisionary-0.2.dist-info/WHEEL
MetaVisionary-0.2.dist-info/entry_points.txt
MetaVisionary-0.2.dist-info/top_level.txt
MetaVisionary-0.2.dist-info/RECORD
