Metadata-Version: 2.2
Name: MetaVisionary
Version: 0.2
Summary: Meta Learning (ProtoMAML) Package
Home-page: https://github.com/subhayudutta/FewShotLearning
Author: Subhayu Dutta
Requires-Dist: tensorflow
Requires-Dist: numpy
Requires-Dist: scikit-learn
Dynamic: author
Dynamic: description
Dynamic: description-content-type
Dynamic: home-page
Dynamic: requires-dist
Dynamic: summary
